LICENSE.txt
README.md
setup.cfg
setup.py
basic_cowin_api.egg-info/PKG-INFO
basic_cowin_api.egg-info/SOURCES.txt
basic_cowin_api.egg-info/dependency_links.txt
basic_cowin_api.egg-info/requires.txt
basic_cowin_api.egg-info/top_level.txt
cowin_api/cowin.py